<annotation>
	<folder>f_3595</folder>
	<filename>peritoneum_a_840.png</filename>
	<path>C:\Users\awick\Desktop\Glenda\annotations\v_9755_s_3548-3624\f_3595\peritoneum_a_840.png</path>
	<source>
		<database>Unknown</database>
	</source>
	<size>
		<width>640</width>
		<height>360</height>
		<depth>1</depth>
	</size>
	<segmented>0</segmented>
	<object>
		<name>endometriosis</name>
		<pose>Unspecified</pose>
		<truncated>0</truncated>
		<difficult>0</difficult>
		<bndbox>
			<xmin>397</xmin>
			<ymin>134</ymin>
			<xmax>461</xmax>
			<ymax>176</ymax>
		</bndbox>
	</object>
</annotation>
