<annotation>
	<folder>f_66</folder>
	<filename>ovary_a_751.png</filename>
	<path>C:\Users\awick\Desktop\Glenda\annotations\v_4371_s_66-320\f_66\ovary_a_751.png</path>
	<source>
		<database>Unknown</database>
	</source>
	<size>
		<width>640</width>
		<height>360</height>
		<depth>1</depth>
	</size>
	<segmented>0</segmented>
	<object>
		<name>endometriosis</name>
		<pose>Unspecified</pose>
		<truncated>0</truncated>
		<difficult>0</difficult>
		<bndbox>
			<xmin>222</xmin>
			<ymin>101</ymin>
			<xmax>502</xmax>
			<ymax>256</ymax>
		</bndbox>
	</object>
</annotation>
